pycontainerutils/__init__.py
pycontainerutils/api/__init__.py
pycontainerutils/api/api_client.py
pycontainerutils/db/BaseDB_Adapter.py
pycontainerutils/db/DB_Adapter.py
pycontainerutils/db/__init__.py
pycontainerutils/db/df_utils.py
pycontainerutils/hello/__init__.py
pycontainerutils/hello/hello1.py
pycontainerutils/logger/__init__.py
pycontainerutils/logger/base_logger_config.py
pycontainerutils/logger/setting_logger.py
pycontainerutils/logger/db/DB_handler.py
pycontainerutils/logger/db/__init__.py
pycontainerutils/logger/db/postgresql_handler.py
pycontainerutils/schedule/__init__.py
pycontainerutils/schedule/schedule_manager.py
tests/__init__.py
tests/api/__init__.py
tests/api/test_api_client.py
tests/db/__init__.py
tests/db/init_test.py
tests/db/test_DB_Adapter.py
tests/db/test_df_utils.py
tests/logger/__init__.py
tests/logger/test_logger_and_DBAdapter.py
tests/logger/test_logger_console.py
tests/logger/test_logger_db.py
pycontainerutils-0.0.2.1.dist-info/LICENSE
pycontainerutils-0.0.2.1.dist-info/METADATA
pycontainerutils-0.0.2.1.dist-info/WHEEL
pycontainerutils-0.0.2.1.dist-info/top_level.txt
pycontainerutils-0.0.2.1.dist-info/RECORD
