Metadata-Version: 2.1
Name: pycontainerutils
Version: 0.0.2.1
Summary: docker container utilities
Home-page: https://github.com/greenrain78
Author: greenrain
Author-email: kdwkdw0078@gmail.com
License: MIT
Platform: UNKNOWN
License-File: LICENSE
Requires-Dist: coloredlogs (>=15.0.1)
Requires-Dist: numpy (>=1.21.4)
Requires-Dist: pandas (>=1.3.4)
Requires-Dist: psycopg2 (>=2.9.2)
Requires-Dist: SQLAlchemy (>=1.4.27)
Requires-Dist: APScheduler (>=3.8.1)
Requires-Dist: xmltodict (>=0.12.0)
